odoo/addons/sale_order_line_note/README.rst
odoo/addons/sale_order_line_note/__init__.py
odoo/addons/sale_order_line_note/__manifest__.py
odoo/addons/sale_order_line_note/i18n/ca.po
odoo/addons/sale_order_line_note/i18n/es.po
odoo/addons/sale_order_line_note/i18n/fr.po
odoo/addons/sale_order_line_note/i18n/it.po
odoo/addons/sale_order_line_note/i18n/nl.po
odoo/addons/sale_order_line_note/i18n/pt.po
odoo/addons/sale_order_line_note/i18n/sale_order_line_note.pot
odoo/addons/sale_order_line_note/i18n/zh_CN.po
odoo/addons/sale_order_line_note/models/__init__.py
odoo/addons/sale_order_line_note/models/sale_order_line.py
odoo/addons/sale_order_line_note/readme/CONTRIBUTOR.rst
odoo/addons/sale_order_line_note/readme/CREDITS.md
odoo/addons/sale_order_line_note/readme/DESCRIPTION.md
odoo/addons/sale_order_line_note/static/description/icon.png
odoo/addons/sale_order_line_note/static/description/index.html
odoo/addons/sale_order_line_note/views/sale_order_view.xml
odoo_addon_sale_order_line_note-19.0.1.0.0.4.dist-info/METADATA
odoo_addon_sale_order_line_note-19.0.1.0.0.4.dist-info/WHEEL
odoo_addon_sale_order_line_note-19.0.1.0.0.4.dist-info/top_level.txt
odoo_addon_sale_order_line_note-19.0.1.0.0.4.dist-info/RECORD
