Metadata-Version: 2.1
Name: odoo-addon-sale_order_line_note
Version: 19.0.1.0.0.4
Requires-Dist: odoo==19.0.*
Summary: Note on sale order line
Home-page: https://github.com/OCA/sale-workflow
License: AGPL-3
Author: Akretion, Odoo Community Association (OCA)
Author-email: support@odoo-community.org
Classifier: Programming Language :: Python
Classifier: Framework :: Odoo
Classifier: Framework :: Odoo :: 19.0
Classifier: License :: OSI Approved :: GNU Affero General Public License v3
